itachip2ir/__init__.py
itachip2ir/device.py
itachip2ir/exception.py
itachip2ir/test_listener.py
itachip2ir-1.3.11.dist-info/METADATA
itachip2ir-1.3.11.dist-info/RECORD
itachip2ir-1.3.11.dist-info/WHEEL
itachip2ir-1.3.11.dist-info/top_level.txt
