Metadata-Version: 2.1
Name: itachip2ir
Version: 1.3.11
Summary: A small Python module for interacting with the Global Cache iTach WF2IR or IP2IR
Home-page: https://github.com/thehappydinoa/itachip2ir
Author: Aidan Holland (thehappydinoa)
Author-email: thehappydinoa@gmail.com
License: UNKNOWN
Project-URL: Bug Reports, https://github.com/thehappydinoa/itachip2ir/issues
Project-URL: Say Thanks!, http://saythanks.io/to/thehappydinoa
Project-URL: Contribute!, https://github.com/thehappydinoa/itachip2ir/pulls
Project-URL: Follow Me!, https://twitter.com/thehappydinoa/
Keywords: itach ip2ir Global Cache ir smart-home
Platform: UNKNOWN
Classifier: Development Status :: 5 - Production/Stable
Classifier: Intended Audience :: Developers
Classifier: Topic :: Software Development :: Build Tools
Classifier: License :: OSI Approved :: MIT License
Classifier: Programming Language :: Python :: 2
Classifier: Programming Language :: Python :: 2.6
Classifier: Programming Language :: Python :: 2.7
Classifier: Programming Language :: Python :: 3
Classifier: Programming Language :: Python :: 3.4
Classifier: Programming Language :: Python :: 3.5
Classifier: Programming Language :: Python :: 3.6
Classifier: Programming Language :: Python :: 3.7
